{"shortTitle":"[FTBQ]","name":"FTB任务","originalName":"FTB Quests","categories":["指南"],"links":[{"href":"https://www.curseforge.com/minecraft/mc-mods/ftb-quests","type":"CurseForge: Forge"},{"href":"https://www.curseforge.com/minecraft/mc-mods/ftb-quests-fabric","type":"CurseForge: Fabric"},{"href":"https://help.ftb.team/help/en-gb/5","type":"WIKI"},{"href":"https://www.mcbbs.net/thread-849746-1-1.html","type":"MCBBS"},{"href":"https://jenkins.latmod.com/job/FTB-Quests/lastSuccessfulBuild/artifact/build/libs/","type":"Jenkins: 1.15下载地址"},{"href":"https://github.com/FTBTeam/FTB-Quests","type":"GitHub"}],"url":"https://www.mcmod.cn/class/1423.html","status":200}