{"shortTitle":"[HTPVZ]","name":"HungTeen的植物大战僵尸","originalName":"HungTeen's Plants vs Zombies Mod","categories":["资源","群落","结构","生物","能源","存储","道具","食物","模型","破坏","指令","国创"],"links":[{"href":"https://www.curseforge.com/minecraft/mc-mods/hungteens-plants-vs-zombies-mod","type":"CurseForge"},{"href":"https://www.mcbbs.net/thread-1052460-1-1.html","type":"MCBBS"},{"href":"https://github.com/HungTeen/pvzmod","type":"GitHub"},{"href":"https://discord.gg/KmnFH4MUGF","type":"Discord"},{"href":"https://space.bilibili.com/362855464","type":"B站: 作者的B站主页"},{"href":"https://wiki.biligame.com/mcplayer/植物大战僵尸（Plants_vs_Zombies）","type":"WIKI: Bilibili Wiki"}],"url":"https://www.mcmod.cn/class/2640.html","status":200}