{"name":"Rand'Ore","categories":["资源","国创"],"links":[{"href":"https://modrinth.com/mod/randore","type":"Modrinth"},{"href":"https://www.curseforge.com/minecraft/mc-mods/randore","type":"CurseForge: Fabric"},{"href":"https://www.curseforge.com/minecraft/mc-mods/randore-forge","type":"CurseForge: Forge"},{"href":"https://github.com/IntelligentCreations/Randore","type":"GitHub: Fabric"},{"href":"https://github.com/IntelligentCreations/Rand-Ore-Forge-Scala","type":"GitHub: Forge"},{"href":"https://dev.azure.com/pkst/_git/Randore","type":"Azure DevOps: Fabric 备用仓库"},{"href":"https://gitee.com/Peakstep/Randore","type":"Gitee"},{"href":"https://www.planetminecraft.com/mod/rand-ore/","type":"PlanetMinecraft"}],"url":"https://www.mcmod.cn/class/4392.html","status":200}