{"shortTitle":"[CW]","name":"中式工坊","originalName":"Chinese Workshop","categories":["资源","道具","模型","中式","建材","国创"],"links":[{"href":"https://www.curseforge.com/minecraft/mc-mods/chineseworkshop","type":"CurseForge"},{"href":"https://github.com/574448121/ChineseWorkshop","type":"GitHub"},{"href":"http://www.mcbbs.net/thread-639428-1-1.html","type":"MCBBS"},{"href":"https://wiki.biligame.com/mcplayer/中式工坊（Chinese_Workshop）","type":"WIKI: Bilibili Wiki"}],"url":"https://www.mcmod.cn/class/891.html","status":200}