{
  "name": "fabric-api-0.104.0+1.21.1.jar",
  "domain": "mods",
  "modrinth": [
    {
      "projectId": "P7dR8mSH",
      "versionId": "qKPgBeHl"
    }
  ],
  "curseforge": [
    {
      "projectId": 306612,
      "fileId": 5710210
    }
  ],
  "fabric": [
    {
      "modId": "fabric-api",
      "version": "0.104.0+1.21.1"
    },
    {
      "modId": "fabric-api-base",
      "version": "0.4.42+6573ed8c19"
    },
    {
      "modId": "fabric-api-lookup-api-v1",
      "version": "1.6.68+b559734419"
    },
    {
      "modId": "fabric-biome-api-v1",
      "version": "13.0.29+5bd9f1bc19"
    },
    {
      "modId": "fabric-block-api-v1",
      "version": "1.0.22+0af3f5a719"
    },
    {
      "modId": "fabric-block-view-api-v2",
      "version": "1.0.10+6573ed8c19"
    },
    {
      "modId": "fabric-blockrenderlayer-v1",
      "version": "1.1.52+0af3f5a719"
    },
    {
      "modId": "fabric-client-tags-api-v1",
      "version": "1.1.15+6573ed8c19"
    },
    {
      "modId": "fabric-command-api-v2",
      "version": "2.2.28+6ced4dd919"
    },
    {
      "modId": "fabric-content-registries-v0",
      "version": "8.0.16+b559734419"
    },
    {
      "modId": "fabric-convention-tags-v2",
      "version": "2.7.0+4053855719"
    },
    {
      "modId": "fabric-crash-report-info-v1",
      "version": "0.2.29+0af3f5a719"
    },
    {
      "modId": "fabric-data-attachment-api-v1",
      "version": "1.1.28+1daea21519"
    },
    {
      "modId": "fabric-data-generation-api-v1",
      "version": "20.2.19+16c4ae2519"
    },
    {
      "modId": "fabric-dimensions-v1",
      "version": "4.0.0+6fc22b9919"
    },
    {
      "modId": "fabric-entity-events-v1",
      "version": "1.7.0+2122d82819"
    },
    {
      "modId": "fabric-events-interaction-v0",
      "version": "0.7.12+ba9dae0619"
    },
    {
      "modId": "fabric-game-rule-api-v1",
      "version": "1.0.53+6ced4dd919"
    },
    {
      "modId": "fabric-item-api-v1",
      "version": "11.0.0+afdfc92119"
    },
    {
      "modId": "fabric-item-group-api-v1",
      "version": "4.1.5+3fc0e55219"
    },
    {
      "modId": "fabric-key-binding-api-v1",
      "version": "1.0.47+0af3f5a719"
    },
    {
      "modId": "fabric-lifecycle-events-v1",
      "version": "2.3.12+6c1df36019"
    },
    {
      "modId": "fabric-loot-api-v3",
      "version": "1.0.2+3f89f5a519"
    },
    {
      "modId": "fabric-message-api-v1",
      "version": "6.0.13+6573ed8c19"
    },
    {
      "modId": "fabric-model-loading-api-v1",
      "version": "2.0.0+fe474d6b19"
    },
    {
      "modId": "fabric-networking-api-v1",
      "version": "4.2.2+60c3209b19"
    },
    {
      "modId": "fabric-object-builder-api-v1",
      "version": "15.2.0+40875a9319"
    },
    {
      "modId": "fabric-particles-v1",
      "version": "4.0.2+6573ed8c19"
    },
    {
      "modId": "fabric-recipe-api-v1",
      "version": "5.0.12+6508971219"
    },
    {
      "modId": "fabric-registry-sync-v0",
      "version": "5.1.2+60c3209b19"
    },
    {
      "modId": "fabric-renderer-api-v1",
      "version": "3.4.0+c705a49c19"
    },
    {
      "modId": "fabric-renderer-indigo",
      "version": "1.7.0+c705a49c19"
    },
    {
      "modId": "fabric-rendering-fluids-v1",
      "version": "3.1.6+1daea21519"
    },
    {
      "modId": "fabric-rendering-v1",
      "version": "5.0.5+df16efd019"
    },
    {
      "modId": "fabric-resource-conditions-api-v1",
      "version": "4.3.0+8dc279b119"
    },
    {
      "modId": "fabric-resource-loader-v0",
      "version": "1.3.0+5659912919"
    },
    {
      "modId": "fabric-screen-api-v1",
      "version": "2.0.25+8b68f1c719"
    },
    {
      "modId": "fabric-screen-handler-api-v1",
      "version": "1.3.86+b559734419"
    },
    {
      "modId": "fabric-sound-api-v1",
      "version": "1.0.23+6573ed8c19"
    },
    {
      "modId": "fabric-transfer-api-v1",
      "version": "5.2.0+d38f898f19"
    },
    {
      "modId": "fabric-transitive-access-wideners-v1",
      "version": "6.1.0+1daea21519"
    },
    {
      "modId": "fabric-command-api-v1",
      "version": "1.2.49+f71b366f19"
    },
    {
      "modId": "fabric-commands-v0",
      "version": "0.2.66+df3654b319"
    },
    {
      "modId": "fabric-convention-tags-v1",
      "version": "2.0.22+7f945d5b19"
    },
    {
      "modId": "fabric-keybindings-v0",
      "version": "0.2.45+df3654b319"
    },
    {
      "modId": "fabric-loot-api-v2",
      "version": "3.0.14+3f89f5a519"
    },
    {
      "modId": "fabric-renderer-registries-v1",
      "version": "3.2.68+df3654b319"
    },
    {
      "modId": "fabric-rendering-data-attachment-v1",
      "version": "0.3.48+73761d2e19"
    },
    {
      "modId": "fabric-rendering-v0",
      "version": "1.1.71+df3654b319"
    }
  ]
}