{
  "name": "redbits-1.16.2.jar",
  "domain": "mods",
  "modrinth": [
    {
      "projectId": "u6AMJBvu",
      "versionId": "jpzYNaO0"
    }
  ],
  "curseforge": [
    {
      "projectId": 403914,
      "fileId": 4786312
    }
  ],
  "fabric": [
    {
      "modId": "redbits-common",
      "version": "1.16.2"
    },
    {
      "modId": "redbits",
      "version": "1.16.2"
    },
    {
      "modId": "redbits",
      "version": "1.16.2"
    },
    {
      "modId": "redbits",
      "version": "1.16.2"
    },
    {
      "modId": "redbits",
      "version": "1.16.2"
    },
    {
      "modId": "redbits",
      "version": "1.16.2"
    },
    {
      "modId": "redbits",
      "version": "1.16.2"
    }
  ]
}