{
  "name": "",
  "domain": "mods",
  "modrinth": [
    {
      "projectId": "qlXnlZLG",
      "versionId": "iyZerA6h"
    }
  ],
  "curseforge": [
    {
      "projectId": 936929,
      "fileId": 5614748
    }
  ],
  "fabric": [
    {
      "modId": "jsonpatcher",
      "version": "1.1.0+mc.1.21.1"
    },
    {
      "modId": "jsonpatcher-lang",
      "version": "1.0.0"
    },
    {
      "modId": "com_github_mattidragon_jsonpatcherlang_jsonpatcher-docs",
      "version": "1.0.0"
    },
    {
      "modId": "config_toolkit",
      "version": "1.1.1"
    }
  ]
}