{
  "name": "frostiful-1.0.7.jar",
  "domain": "mods",
  "modrinth": [
    {
      "projectId": "Ae6qoBj3",
      "versionId": "GyHfmfTn"
    }
  ],
  "curseforge": [
    {
      "projectId": 715248,
      "fileId": 5214988
    }
  ],
  "fabric": [
    {
      "modId": "frostiful",
      "version": "1.0.7"
    },
    {
      "modId": "mm",
      "version": "2.3"
    },
    {
      "modId": "cardinal-components-base",
      "version": "5.2.1"
    },
    {
      "modId": "cardinal-components-entity",
      "version": "5.2.1"
    }
  ]
}