{
  "name": "spwallet-1.20-2.1.2.jar",
  "domain": "mods",
  "modrinth": [
    {
      "projectId": "KMOm6R86",
      "versionId": "nm9G9RJL"
    }
  ],
  "curseforge": [
    {
      "projectId": 662188,
      "fileId": 4719029
    }
  ],
  "fabric": [
    {
      "modId": "spwallet",
      "version": "1.20-2.1.2"
    },
    {
      "modId": "cloth-config",
      "version": "11.1.106"
    },
    {
      "modId": "libninepatch",
      "version": "1.2.0"
    },
    {
      "modId": "blue_endless_jankson",
      "version": "1.2.1"
    }
  ]
}